pymgpipe/__init__.py
pymgpipe/coupling.py
pymgpipe/diet.py
pymgpipe/fva.py
pymgpipe/io.py
pymgpipe/logger.py
pymgpipe/main.py
pymgpipe/metrics.py
pymgpipe/modeling.py
pymgpipe/nmpc.py
pymgpipe/utils.py
pymgpipe/resources/diets/AverageEuropeanDiet.txt
pymgpipe/resources/diets/DACHDiet.txt
pymgpipe/resources/diets/GlutenFreeDiet.txt
pymgpipe/resources/diets/HighFatLowCarbDiet.txt
pymgpipe/resources/diets/HighFiberDiet.txt
pymgpipe/resources/diets/HighProteinDiet.txt
pymgpipe/resources/diets/MediterraneanDiet.txt
pymgpipe/resources/diets/Type2DiabetesDiet.txt
pymgpipe/resources/diets/UnhealthyDiet.txt
pymgpipe/resources/diets/VeganDiet.txt
pymgpipe/resources/diets/VegetarianDiet.txt
pymgpipe/resources/miniTaxa/TaxaA.xml.gz
pymgpipe/resources/miniTaxa/TaxaB.xml.gz
pymgpipe/resources/miniTaxa/TaxaC.xml.gz
pymgpipe/resources/miniTaxa/TaxaD.xml.gz
pymgpipe/resources/models/mini_model.json
pymgpipe/resources/models/mini_model.mat
pymgpipe/resources/models/mini_model.xml
pymgpipe/resources/models/mini_model.xml.gz
pymgpipe/resources/problems/mini_model.lp
pymgpipe/resources/problems/mini_model.lp.gz
pymgpipe/resources/problems/mini_model.mps
pymgpipe/resources/problems/mini_model.mps.gz
pymgpipe-0.16.10.dist-info/LICENSE
pymgpipe-0.16.10.dist-info/METADATA
pymgpipe-0.16.10.dist-info/WHEEL
pymgpipe-0.16.10.dist-info/top_level.txt
pymgpipe-0.16.10.dist-info/RECORD
