Metadata-Version: 2.1
Name: pymgpipe
Version: 0.16.10
Summary: Community level microbiome metabolic modeling in Python
Home-page: https://github.com/korem-lab/pymgpipe
Author: Yoli Meydan, Federico Baldini, Tal Korem
Author-email: ym2877@cumc.columbia.edu, fb2557@cumc.columbia.edu, tk2829@cumc.columbia.edu
License: Apache-2.0
Project-URL: Issues, https://github.com/korem-lab/pymgpipe/issues
Project-URL: Source, https://github.com/korem-lab/pymgpipe
Project-URL: Readme, https://github.com/korem-lab/pymgpipe/blob/main/README.md
Classifier: Intended Audience :: Healthcare Industry
Classifier: Intended Audience :: Information Technology
Classifier: Intended Audience :: Science/Research
Classifier: License :: OSI Approved :: Apache Software License
Classifier: Programming Language :: Python :: 3
Classifier: Topic :: Scientific/Engineering
Requires-Python: >=3
License-File: LICENSE
Requires-Dist: cobra
Requires-Dist: optlang
Requires-Dist: scikit-bio
Requires-Dist: tqdm
Requires-Dist: seaborn
Requires-Dist: gurobipy
